odoo/addons/sale_order_warehouse_from_delivery_carrier/README.rst
odoo/addons/sale_order_warehouse_from_delivery_carrier/__init__.py
odoo/addons/sale_order_warehouse_from_delivery_carrier/__manifest__.py
odoo/addons/sale_order_warehouse_from_delivery_carrier/i18n/it.po
odoo/addons/sale_order_warehouse_from_delivery_carrier/i18n/nl.po
odoo/addons/sale_order_warehouse_from_delivery_carrier/i18n/sale_order_warehouse_from_delivery_carrier.pot
odoo/addons/sale_order_warehouse_from_delivery_carrier/models/__init__.py
odoo/addons/sale_order_warehouse_from_delivery_carrier/models/delivery_carrier.py
odoo/addons/sale_order_warehouse_from_delivery_carrier/models/sale_order.py
odoo/addons/sale_order_warehouse_from_delivery_carrier/readme/CONFIGURE.md
odoo/addons/sale_order_warehouse_from_delivery_carrier/readme/CONTRIBUTORS.md
odoo/addons/sale_order_warehouse_from_delivery_carrier/readme/DESCRIPTION.md
odoo/addons/sale_order_warehouse_from_delivery_carrier/readme/USAGE.md
odoo/addons/sale_order_warehouse_from_delivery_carrier/static/description/icon.png
odoo/addons/sale_order_warehouse_from_delivery_carrier/static/description/index.html
odoo/addons/sale_order_warehouse_from_delivery_carrier/tests/__init__.py
odoo/addons/sale_order_warehouse_from_delivery_carrier/tests/test_module_flow.py
odoo/addons/sale_order_warehouse_from_delivery_carrier/views/delivery_carrier_views.xml
odoo_addon_sale_order_warehouse_from_delivery_carrier-18.0.1.0.0.2.dist-info/METADATA
odoo_addon_sale_order_warehouse_from_delivery_carrier-18.0.1.0.0.2.dist-info/WHEEL
odoo_addon_sale_order_warehouse_from_delivery_carrier-18.0.1.0.0.2.dist-info/top_level.txt
odoo_addon_sale_order_warehouse_from_delivery_carrier-18.0.1.0.0.2.dist-info/RECORD
